{
  "version": 1,
  "updated_at": "2026-03-30T05:25:14.412Z",
  "items": [
    {
      "id": "deep-research-report",
      "type": "doc",
      "display_title": "",
      "author": "",
      "summary": "",
      "tags": [],
      "featured": false,
      "manual_order": null,
      "visibility": "archived",
      "metadata_updated_at": "2026-03-30T05:25:14.412Z",
      "source": "deep_research_report.md"
    },
    {
      "id": "designing-data-intensive-applications-2nd-edition",
      "type": "book",
      "display_title": "",
      "author": "",
      "summary": "",
      "tags": [],
      "featured": false,
      "manual_order": null,
      "visibility": "archived",
      "metadata_updated_at": "2026-03-30T05:25:14.412Z",
      "source": "Designing Data-Intensive Applications, 2nd Edition.pdf"
    },
    {
      "id": "progit",
      "type": "book",
      "display_title": "",
      "author": "",
      "summary": "",
      "tags": [],
      "featured": false,
      "manual_order": null,
      "visibility": "archived",
      "metadata_updated_at": "2026-03-30T05:25:14.412Z",
      "source": "progit.pdf"
    }
  ]
}
